pointofvue/__init__.py
pointofvue/context.py
pointofvue/settings.py
pointofvue/templates/script.html
pointofvue/templates/script_vue3.html
pointofvue/templatetags/__init__.py
pointofvue/templatetags/pointofvue.py
pointofvue-0.1.1.dist-info/METADATA
pointofvue-0.1.1.dist-info/WHEEL
pointofvue-0.1.1.dist-info/top_level.txt
pointofvue-0.1.1.dist-info/RECORD
